README
setup.py
dsl_tools/__init__.py
python_dsl_tools.egg-info/PKG-INFO
python_dsl_tools.egg-info/SOURCES.txt
python_dsl_tools.egg-info/dependency_links.txt
python_dsl_tools.egg-info/top_level.txt