Metadata-Version: 1.0
Name: python-dsl-tools
Version: 0.2.0
Summary: UNKNOWN
Home-page: https://github.com/gabrielgrant/python-dsl-tools
Author: Gabriel Grant
Author-email: g@briel.ca
License: LGPL
Platform: UNKNOWN
